abdal_net_py/__init__.py
abdal_net_py/abdal_net_py_about.py
abdal_net_py/abdal_net_py_admin.py
abdal_net_py/abdal_net_py_generator.py
abdal_net_py/abdal_net_py_loger.py
abdal_net_py/abdal_net_py_unit.py
abdal_net_py-2.9.dist-info/LICENSE
abdal_net_py-2.9.dist-info/METADATA
abdal_net_py-2.9.dist-info/WHEEL
abdal_net_py-2.9.dist-info/top_level.txt
abdal_net_py-2.9.dist-info/RECORD
