Metadata-Version: 2.1
Name: abdal-net-py
Version: 2.9
Summary: Powerful security network package
Home-page: https://github.com/abdal-security-group/abdal-net-py
Author: Ebrahim Shafiei (EbraSha)
Author-email: Prof.Shafiei@Gmail.com
License: UNKNOWN
Project-URL: Bug Tracker, https://github.com/abdal-security-group/abdal-net-py/issues
Keywords: python,security,hack,network,camera stream,sockets
Platform: UNKNOWN
Classifier: Development Status :: 5 - Production/Stable
Classifier: Intended Audience :: Developers
Classifier: Intended Audience :: Information Technology
Classifier: Intended Audience :: System Administrators
Classifier: Intended Audience :: Science/Research
Classifier: Programming Language :: Python :: 3
Classifier: Operating System :: Unix
Classifier: Operating System :: MacOS :: MacOS X
Classifier: Operating System :: Microsoft :: Windows
License-File: LICENSE
Requires-Dist: hurry.filesize
Requires-Dist: psutil
